animalpy/__init__.py
animalpy-0.1.5.post3.dist-info/WHEEL
animalpy-0.1.5.post3.dist-info/METADATA
animalpy-0.1.5.post3.dist-info/RECORD
