Metadata-Version: 2.1
Name: animalpy
Version: 0.1.5.post3
Summary: Python wrapper using some-random-api.ml that can get animal images and facts with easy plug-and-play syntax!
Home-page: https://github.com/ksIsCute/Animals.py
License: MIT
Author: ksIsCute
Author-email: thebeast47ytbusiness@gmail.com
Maintainer: ksIsCute
Maintainer-email: thebeast47ytbusiness@gmail.com
Requires-Python: >=3.8,<4.0
Classifier: License :: OSI Approved :: MIT License
Classifier: Programming Language :: Python :: 3
Classifier: Programming Language :: Python :: 3.10
Classifier: Programming Language :: Python :: 3.8
Classifier: Programming Language :: Python :: 3.9
Project-URL: Repository, https://github.com/ksIsCute/Animals.py
